MANIFEST.in
README.rst
ip_associations_python_novaclient_ext.py
setup.py
ip_associations_python_novaclient_ext.egg-info/PKG-INFO
ip_associations_python_novaclient_ext.egg-info/SOURCES.txt
ip_associations_python_novaclient_ext.egg-info/dependency_links.txt
ip_associations_python_novaclient_ext.egg-info/requires.txt
ip_associations_python_novaclient_ext.egg-info/top_level.txt