Metadata-Version: 1.1
Name: ip-associations-python-novaclient-ext
Version: 0.2
Summary: Adds Rackspace ip_associations support to python-novaclient
Home-page: https://github.com/rackerlabs/ip_associations_python_novaclient_ext
Author: Rackspace
Author-email: neutron-requests@lists.rackspace.com
License: Apache License, Version 2.0
Platform: UNKNOWN
Classifier: Development Status :: 5 - Production/Stable
Classifier: Environment :: Console
Classifier: Intended Audience :: Developers
Classifier: Intended Audience :: Information Technology
Classifier: License :: OSI Approved :: Apache Software License
Classifier: Operating System :: OS Independent
Classifier: Environment :: OpenStack
Classifier: Programming Language :: Python
